custom_utils/__init__.py
custom_utils/config.py
custom_utils/exceptions.py
custom_utils/utils.py
custom_utils/alerter/__init__.py
custom_utils/alerter/slack.py
custom_utils/configurer/__init__.py
custom_utils/configurer/profiler.py
custom_utils/configurer/utils.py
custom_utils/connector/__init__.py
custom_utils/connector/bigquery.py
custom_utils/connector/mongodb.py
custom_utils/connector/mysql.py
custom_utils/connector/s3.py
custom_utils-0.0.313.dist-info/LICENSE
custom_utils-0.0.313.dist-info/METADATA
custom_utils-0.0.313.dist-info/WHEEL
custom_utils-0.0.313.dist-info/top_level.txt
custom_utils-0.0.313.dist-info/RECORD
