Metadata-Version: 2.1
Name: custom-utils
Version: 0.0.313
Summary: Utilities for database connectors, slack alerter, loggers etc
Home-page: https://github.com/RahulnKumar/custom-utils
Author: Rahul Kumar
Author-email: rahulnkumar7@gmail.com
Classifier: Development Status :: 2 - Pre-Alpha
Classifier: Programming Language :: Python :: 3.6
Classifier: Topic :: Scientific/Engineering :: Artificial Intelligence
Requires-Python: >=3.6.9
License-File: LICENSE
Requires-Dist: python-dotenv
Requires-Dist: subprocess32
Provides-Extra: bigquery
Requires-Dist: tqdm (==4.49.0) ; extra == 'bigquery'
Requires-Dist: google-cloud-bigquery (==2.1.0) ; extra == 'bigquery'
Requires-Dist: pandas-gbq ; extra == 'bigquery'
Requires-Dist: google-cloud ; extra == 'bigquery'
Provides-Extra: full
Requires-Dist: mysql-connector-python ; extra == 'full'
Requires-Dist: google-cloud ; extra == 'full'
Requires-Dist: google-cloud-bigquery (==2.1.0) ; extra == 'full'
Requires-Dist: boto ; extra == 'full'
Requires-Dist: joblib ; extra == 'full'
Requires-Dist: SQLAlchemy ; extra == 'full'
Requires-Dist: slack-sdk (==3.21.3) ; extra == 'full'
Requires-Dist: boto3 ; extra == 'full'
Requires-Dist: pandas-gbq ; extra == 'full'
Requires-Dist: tqdm (==4.49.0) ; extra == 'full'
Requires-Dist: pymongo (==3.10.0) ; extra == 'full'
Provides-Extra: mongodb
Requires-Dist: pymongo (==3.10.0) ; extra == 'mongodb'
Provides-Extra: mysql
Requires-Dist: SQLAlchemy ; extra == 'mysql'
Requires-Dist: mysql-connector-python ; extra == 'mysql'
Provides-Extra: s3
Requires-Dist: boto ; extra == 's3'
Requires-Dist: boto3 ; extra == 's3'
Requires-Dist: joblib ; extra == 's3'
Provides-Extra: slack
Requires-Dist: slack-sdk (==3.21.3) ; extra == 'slack'
